README.md
setup.py
naf2conll/__init__.py
naf2conll/__main__.py
naf2conll/conll_converters.py
naf2conll/conll_writers.py
naf2conll/constants.py
naf2conll/main.py
naf2conll/naf_readers.py
naf2conll/util.py
naf2conll.egg-info/PKG-INFO
naf2conll.egg-info/SOURCES.txt
naf2conll.egg-info/dependency_links.txt
naf2conll.egg-info/requires.txt
naf2conll.egg-info/top_level.txt