Metadata-Version: 2.1
Name: naf2conll
Version: 1.0.0
Summary: Script to convert files in NAF format to CoNLL format
Home-page: https://github.com/cltl/FormatConversions/tree/master/naf2conll
Author: Martin van Harmelen
Author-email: Martin@vanharmelen.com
License: UNKNOWN
Platform: UNKNOWN
Classifier: Intended Audience :: Developers
Classifier: Intended Audience :: Science/Research
Classifier: License :: OSI Approved :: Apache Software License
Classifier: Development Status :: 5 - Production/Stable
Classifier: Programming Language :: Python :: 3.6
